odoo/addons/sale_order_product_recommendation_secondary_unit/README.rst
odoo/addons/sale_order_product_recommendation_secondary_unit/__init__.py
odoo/addons/sale_order_product_recommendation_secondary_unit/__manifest__.py
odoo/addons/sale_order_product_recommendation_secondary_unit/i18n/es.po
odoo/addons/sale_order_product_recommendation_secondary_unit/i18n/sale_order_product_recommendation_secondary_unit.pot
odoo/addons/sale_order_product_recommendation_secondary_unit/readme/CONFIGURE.rst
odoo/addons/sale_order_product_recommendation_secondary_unit/readme/CONTRIBUTORS.rst
odoo/addons/sale_order_product_recommendation_secondary_unit/readme/DESCRIPTION.rst
odoo/addons/sale_order_product_recommendation_secondary_unit/readme/USAGE.rst
odoo/addons/sale_order_product_recommendation_secondary_unit/static/description/icon.png
odoo/addons/sale_order_product_recommendation_secondary_unit/static/description/index.html
odoo/addons/sale_order_product_recommendation_secondary_unit/tests/__init__.py
odoo/addons/sale_order_product_recommendation_secondary_unit/tests/test_recommendations.py
odoo/addons/sale_order_product_recommendation_secondary_unit/wizards/__init__.py
odoo/addons/sale_order_product_recommendation_secondary_unit/wizards/sale_order_recommendation.py
odoo/addons/sale_order_product_recommendation_secondary_unit/wizards/sale_order_recommendation_view.xml
odoo13_addon_sale_order_product_recommendation_secondary_unit-13.0.2.2.0.dist-info/METADATA
odoo13_addon_sale_order_product_recommendation_secondary_unit-13.0.2.2.0.dist-info/WHEEL
odoo13_addon_sale_order_product_recommendation_secondary_unit-13.0.2.2.0.dist-info/top_level.txt
odoo13_addon_sale_order_product_recommendation_secondary_unit-13.0.2.2.0.dist-info/RECORD
