Metadata-Version: 2.1
Name: odoo13-addon-sale-order-product-recommendation-secondary-unit
Version: 13.0.2.2.0
Summary: Add secondary unit to recommend products wizard
Home-page: https://github.com/OCA/sale-workflow
Author: Tecnativa, Odoo Community Association (OCA)
Author-email: support@odoo-community.org
License: AGPL-3
Platform: UNKNOWN
Classifier: Programming Language :: Python
Classifier: Framework :: Odoo
Classifier: License :: OSI Approved :: GNU Affero General Public License v3
Requires-Python: >=3.5
Requires-Dist: odoo13-addon-sale-order-product-recommendation
Requires-Dist: odoo13-addon-sale-order-secondary-unit
Requires-Dist: odoo (<13.1dev,>=13.0a)
